csu_radartools/__init__.py
csu_radartools/_version.py
csu_radartools/beta_functions.py
csu_radartools/calc_kdp_ray_fir.cpython-36m-darwin.so
csu_radartools/common.py
csu_radartools/csu_blended_rain.py
csu_radartools/csu_blended_rain_tropical.py
csu_radartools/csu_dsd.py
csu_radartools/csu_fhc.py
csu_radartools/csu_kdp.py
csu_radartools/csu_liquid_ice_mass.py
csu_radartools/csu_misc.py
csu_radartools/fundamentals.py
csu_radartools/beta_function_parameters/C-band_Correlation_Coefficient.csv
csu_radartools/beta_function_parameters/C-band_Differential_Reflectivity.csv
csu_radartools/beta_function_parameters/C-band_Linear_Depolarization_Ratio.csv
csu_radartools/beta_function_parameters/C-band_Reflectivity.csv
csu_radartools/beta_function_parameters/C-band_Specific_Differential_Phase.csv
csu_radartools/beta_function_parameters/C-band_Temperature.csv
csu_radartools/beta_function_parameters/S-band_Correlation_Coefficient.csv
csu_radartools/beta_function_parameters/S-band_Differential_Reflectivity.csv
csu_radartools/beta_function_parameters/S-band_Linear_Depolarization_Ratio.csv
csu_radartools/beta_function_parameters/S-band_Reflectivity.csv
csu_radartools/beta_function_parameters/S-band_Specific_Differential_Phase.csv
csu_radartools/beta_function_parameters/S-band_Temperature.csv
csu_radartools/beta_function_parameters/X-band_Correlation_Coefficient.csv
csu_radartools/beta_function_parameters/X-band_Differential_Reflectivity.csv
csu_radartools/beta_function_parameters/X-band_Linear_Depolarization_Ratio.csv
csu_radartools/beta_function_parameters/X-band_Reflectivity.csv
csu_radartools/beta_function_parameters/X-band_Specific_Differential_Phase.csv
csu_radartools/beta_function_parameters/X-band_Temperature.csv
csu_radartools-1.3.0.dist-info/LICENSE.txt
csu_radartools-1.3.0.dist-info/METADATA
csu_radartools-1.3.0.dist-info/WHEEL
csu_radartools-1.3.0.dist-info/top_level.txt
csu_radartools-1.3.0.dist-info/RECORD
